{
  "success": true,
  "model": {
    "count": 4,
    "uidFilter":{
      "94B34E8152D43232233891FA34529B38":true,
      "9430BB2DF7604F9E3D227AB849137CFE":true,
      "F22045983B504A26C0D9C2572966C591":true,
      "6E6845904CC1FB99E4EAB82E5E813EB2":true
    },
    "list": [
      {
        "song": {
          "url": "http://k186studio.com/static/music/94B34E8152D43232233891FA34529B38.mp3",
          "poster": "http://k186studio.com/static/music/poster/94B34E8152D43232233891FA34529B38.jpg",
          "title": "平凡之路 (《后会无期》电影主题曲)",
          "artist": "朴树",
          "album": "平凡之路",
          "uid": "94B34E8152D43232233891FA34529B38",
          "markTitle": {
            "quality": 2,
            "exclusive": 1,
            "mv": 1
          }
        },
        "mark": {
          "isDownload": true,
          "isInternet": false
        }
      },
      {
        "song": {
          "url": "http://k186studio.com/static/music/9430BB2DF7604F9E3D227AB849137CFE.mp3",
          "poster": "http://k186studio.com/static/music/poster/9430BB2DF7604F9E3D227AB849137CFE.jpg",
          "title": "恋曲1990 (《阿郎的故事》国语版电影主题曲_《阿郎恋曲》国语版)",
          "artist": "罗大佑",
          "album": "爱人同志（台湾版）",
          "uid": "9430BB2DF7604F9E3D227AB849137CFE",
          "markTitle": {
            "quality": 2,
            "exclusive": 1,
            "mv": 1
          }
        },
        "mark": {
          "isDownload": true,
          "isInternet": false
        }
      },
      {
        "song": {
          "url": "http://k186studio.com/static/music/F22045983B504A26C0D9C2572966C591.mp3",
          "poster": "http://k186studio.com/static/music/poster/F22045983B504A26C0D9C2572966C591.jpg",
          "title": "想神马有神马",
          "artist": "李代沫",
          "album": "想神马有神马",
          "uid": "F22045983B504A26C0D9C2572966C591",
          "markTitle": {
            "quality": 2,
            "exclusive": 1,
            "mv": 1
          }
        },
        "mark": {
          "isDownload": true,
          "isInternet": false
        }
      },
      {
        "song": {
          "url": "http://k186studio.com/static/music/6E6845904CC1FB99E4EAB82E5E813EB2.mp3",
          "poster": "http://k186studio.com/static/music/poster/6E6845904CC1FB99E4EAB82E5E813EB2.jpg",
          "title": "美丽的神话 (《功夫瑜伽》电影主题曲)",
          "artist": "成龙",
          "album": "美丽的神话",
          "uid": "6E6845904CC1FB99E4EAB82E5E813EB2",
          "markTitle": {
            "quality": 2,
            "exclusive": 1,
            "mv": 1
          }
        },
        "mark": {
          "isDownload": true,
          "isInternet": false
        }
      }
    ]
  }
}